gliner/__init__.py
gliner/config.py
gliner/model.py
gliner/utils.py
gliner/data_processing/__init__.py
gliner/data_processing/collator.py
gliner/data_processing/dataset.py
gliner/data_processing/processor.py
gliner/data_processing/tokenizer.py
gliner/data_processing/utils.py
gliner/decoding/__init__.py
gliner/decoding/decoder.py
gliner/decoding/utils.py
gliner/decoding/trie/__init__.py
gliner/decoding/trie/python_labels_trie.py
gliner/evaluation/__init__.py
gliner/evaluation/evaluate.py
gliner/evaluation/evaluator.py
gliner/modeling/__init__.py
gliner/modeling/base.py
gliner/modeling/decoder.py
gliner/modeling/encoder.py
gliner/modeling/layers.py
gliner/modeling/loss_functions.py
gliner/modeling/scorers.py
gliner/modeling/span_rep.py
gliner/multitask/__init__.py
gliner/multitask/base.py
gliner/multitask/classification.py
gliner/multitask/open_extraction.py
gliner/multitask/question_answering.py
gliner/multitask/relation_extraction.py
gliner/multitask/summarization.py
gliner/onnx/__init__.py
gliner/onnx/model.py
gliner/training/__init__.py
gliner/training/trainer.py
gliner-0.2.22.dist-info/licenses/LICENSE
gliner-0.2.22.dist-info/METADATA
gliner-0.2.22.dist-info/WHEEL
gliner-0.2.22.dist-info/top_level.txt
gliner-0.2.22.dist-info/RECORD
