Metadata-Version: 2.4
Name: gliner
Version: 0.2.22
Summary: Generalist model for NER (Extract any entity types from texts)
Author: Urchade Zaratiana, Nadi Tomeh, Pierre Holat, Thierry Charnois
Maintainer: Urchade Zaratiana
License: Apache-2.0
Project-URL: Homepage, https://github.com/urchade/GLiNER
Keywords: named-entity-recognition,ner,data-science,natural-language-processing,artificial-intelligence,nlp,machine-learning,transformers
Requires-Python: >=3.8
License-File: LICENSE
Requires-Dist: torch>=2.0.0
Requires-Dist: transformers<=4.51.0,>=4.38.2
Requires-Dist: huggingface_hub>=0.21.4
Requires-Dist: tqdm
Requires-Dist: onnxruntime
Requires-Dist: sentencepiece
Provides-Extra: gpu
Requires-Dist: onnxruntime-gpu; extra == "gpu"
Provides-Extra: tokenizers
Requires-Dist: langdetect; extra == "tokenizers"
Requires-Dist: python-mecab-ko; extra == "tokenizers"
Requires-Dist: janome; extra == "tokenizers"
Requires-Dist: jieba3; extra == "tokenizers"
Requires-Dist: camel_tools; extra == "tokenizers"
Requires-Dist: indic-nlp-library; extra == "tokenizers"
Requires-Dist: spacy; extra == "tokenizers"
Requires-Dist: stanza; extra == "tokenizers"
Provides-Extra: stanza
Requires-Dist: stanza; extra == "stanza"
Requires-Dist: langdetect; extra == "stanza"
Dynamic: license-file
